gmshparser/__init__.py
gmshparser/abstract_parser.py
gmshparser/cli.py
gmshparser/element.py
gmshparser/element_entity.py
gmshparser/elements_parser.py
gmshparser/elements_parser_v1.py
gmshparser/elements_parser_v2.py
gmshparser/helpers.py
gmshparser/main_parser.py
gmshparser/mesh.py
gmshparser/mesh_format_parser.py
gmshparser/node.py
gmshparser/node_entity.py
gmshparser/nodes_parser.py
gmshparser/nodes_parser_v1.py
gmshparser/nodes_parser_v2.py
gmshparser/version_manager.py
gmshparser-0.3.1.dist-info/LICENSE
gmshparser-0.3.1.dist-info/METADATA
gmshparser-0.3.1.dist-info/WHEEL
gmshparser-0.3.1.dist-info/RECORD
