Metadata-Version: 2.3
Name: gmshparser
Version: 0.3.1
Summary: gmshparser is a lightweight, 100 % tested and well documented package that parses Gmsh ascii file format (.msh)
Author: Jukka Aho
Author-email: ahojukka5@gmail.com
Requires-Python: >=3.12,<4.0
Classifier: Programming Language :: Python :: 3
Classifier: Programming Language :: Python :: 3.12
Classifier: Programming Language :: Python :: 3.13
